addon_utils/__init__.pyi
addon_utils/py.typed
animsys_refactor/__init__.pyi
animsys_refactor/py.typed
aud/__init__.pyi
aud/py.typed
bge/__init__.pyi
bge/py.typed
bge/app/__init__.pyi
bge/constraints/__init__.pyi
bge/types/__init__.pyi
bge_extras/__init__.pyi
bge_extras/py.typed
bge_extras/logger/__init__.pyi
bgl/__init__.pyi
bgl/py.typed
bgui/__init__.pyi
bgui/py.typed
bgui/frame/__init__.pyi
bgui/frame_button/__init__.pyi
bgui/image/__init__.pyi
bgui/image_button/__init__.pyi
bgui/label/__init__.pyi
bgui/list_box/__init__.pyi
bgui/progress_bar/__init__.pyi
bgui/system/__init__.pyi
bgui/text_block/__init__.pyi
bgui/text_input/__init__.pyi
bgui/theme/__init__.pyi
bgui/widget/__init__.pyi
bl_app_override/__init__.pyi
bl_app_override/py.typed
bl_app_override/helpers/__init__.pyi
bl_app_template_utils/__init__.pyi
bl_app_template_utils/py.typed
bl_console_utils/__init__.pyi
bl_console_utils/py.typed
bl_console_utils/autocomplete/__init__.pyi
bl_console_utils/autocomplete/complete_calltip/__init__.pyi
bl_console_utils/autocomplete/complete_import/__init__.pyi
bl_console_utils/autocomplete/complete_namespace/__init__.pyi
bl_console_utils/autocomplete/intellisense/__init__.pyi
bl_i18n_utils/__init__.pyi
bl_i18n_utils/py.typed
bl_i18n_utils/bl_extract_messages/__init__.pyi
bl_i18n_utils/merge_po/__init__.pyi
bl_i18n_utils/settings/__init__.pyi
bl_i18n_utils/utils/__init__.pyi
bl_i18n_utils/utils_cli/__init__.pyi
bl_i18n_utils/utils_languages_menu/__init__.pyi
bl_i18n_utils/utils_rtl/__init__.pyi
bl_keymap_utils/__init__.pyi
bl_keymap_utils/py.typed
bl_keymap_utils/io/__init__.pyi
bl_keymap_utils/keymap_from_toolbar/__init__.pyi
bl_keymap_utils/keymap_hierarchy/__init__.pyi
bl_keymap_utils/platform_helpers/__init__.pyi
bl_keymap_utils/versioning/__init__.pyi
bl_math/__init__.pyi
bl_math/py.typed
bl_operators/__init__.pyi
bl_operators/py.typed
bl_operators/add_mesh_torus/__init__.pyi
bl_operators/anim/__init__.pyi
bl_operators/assets/__init__.pyi
fake_bge_module_0.36-20250202.dist-info/METADATA
fake_bge_module_0.36-20250202.dist-info/WHEEL
fake_bge_module_0.36-20250202.dist-info/top_level.txt
fake_bge_module_0.36-20250202.dist-info/RECORD
