Metadata-Version: 2.2
Name: fake-bge-module-0.36
Version: 20250202
Summary: Collection of the fake Blender Game Engine (BGE) Python API module for the code completion.
Author: nutti
Author-email: nutti.metro@gmail.com
Maintainer: nutti
Maintainer-email: nutti.metro@gmail.com
Project-URL: Homepage, https://github.com/nutti/fake-bge-module
Project-URL: Documentation, https://github.com/nutti/fake-bge-module/blob/main/README.md
Project-URL: Source, https://github.com/nutti/fake-bge-module
Project-URL: Download, https://github.com/nutti/fake-bge-module/releases
Project-URL: Bug Tracker, https://github.com/nutti/fake-bge-module/issues
Project-URL: Release Notes, https://github.com/nutti/fake-bge-module/blob/main/CHANGELOG.md
Platform: Windows
Platform: Linux
Platform: Mac OS-X
Classifier: Topic :: Multimedia :: Graphics :: 3D Modeling
Classifier: Topic :: Multimedia :: Graphics :: 3D Rendering
Classifier: Topic :: Text Editors :: Integrated Development Environments (IDE)
Classifier: Programming Language :: Python
Classifier: Programming Language :: Python :: 3
Classifier: License :: OSI Approved :: MIT License
Requires-Python: >=3.8
